wcc_timetable_generator/__init__.py
wcc_timetable_generator/__main__.py
wcc_timetable_generator/algo.py
wcc_timetable_generator/components/__init__.py
wcc_timetable_generator/components/entry.py
wcc_timetable_generator/subject_model.py
wcc_timetable_generator/timetable.css
wcc_timetable_generator/timetable.py
wcc_timetable_generator-1.2.1.dist-info/entry_points.txt
wcc_timetable_generator-1.2.1.dist-info/WHEEL
wcc_timetable_generator-1.2.1.dist-info/METADATA
wcc_timetable_generator-1.2.1.dist-info/RECORD
