Metadata-Version: 2.1
Name: wcc-timetable-generator
Version: 1.2.1
Summary: 
Author: Tsierenana Bôtramanagna Gracy
Author-email: gtsierenana@gmail.com
Requires-Python: >=3.8,<4.0
Classifier: Programming Language :: Python :: 3
Classifier: Programming Language :: Python :: 3.8
Classifier: Programming Language :: Python :: 3.9
Classifier: Programming Language :: Python :: 3.10
Requires-Dist: textual (>=0.29.0,<0.30.0)
